moudle/__init__.py
moudle/core.py
ragcheckerzhongshui0911-0.0.1.dist-info/LICENSE
ragcheckerzhongshui0911-0.0.1.dist-info/METADATA
ragcheckerzhongshui0911-0.0.1.dist-info/WHEEL
ragcheckerzhongshui0911-0.0.1.dist-info/top_level.txt
ragcheckerzhongshui0911-0.0.1.dist-info/RECORD
